choropleth_gen/__init__.py
choropleth_gen/choropleth.py
choropleth_gen/gen_greyscale_choropleth.py
choropleth_gen/gen_spectral_choropleth.py
choropleth_gen-0.2.dist-info/DESCRIPTION.rst
choropleth_gen-0.2.dist-info/METADATA
choropleth_gen-0.2.dist-info/RECORD
choropleth_gen-0.2.dist-info/WHEEL
choropleth_gen-0.2.dist-info/entry_points.txt
choropleth_gen-0.2.dist-info/metadata.json
choropleth_gen-0.2.dist-info/top_level.txt
