Metadata-Version: 2.0
Name: choropleth-gen
Version: 0.2
Summary: Utilities for ASCII encoded hexagonal grids
Home-page: https://github.com/ldesousa/choropleth-gen
Author: Luís Moreira de Sousa
Author-email: luis.de.sousa@protonmail.ch
License: EUPL v1.1
Keywords: choropleth QGis SLD
Platform: UNKNOWN
Classifier: Programming Language :: Python
Classifier: Programming Language :: Python :: 3
Classifier: Development Status :: 4 - Beta
Classifier: Environment :: Console
Classifier: Intended Audience :: Science/Research
Classifier: License :: OSI Approved :: European Union Public Licence 1.1 (EUPL 1.1)
Classifier: Operating System :: OS Independent
Classifier: Topic :: Scientific/Engineering :: GIS
Requires-Dist: pyparsing
